sql_to_cosmos.py
sql_to_cosmos-0.0.2.dist-info/LICENSE
sql_to_cosmos-0.0.2.dist-info/METADATA
sql_to_cosmos-0.0.2.dist-info/WHEEL
sql_to_cosmos-0.0.2.dist-info/top_level.txt
sql_to_cosmos-0.0.2.dist-info/RECORD
