Metadata-Version: 2.1
Name: sql-to-cosmos
Version: 0.0.2
Summary: Python package for migrating data from SQL to CosmosDB
Author: Marco Cardoso
License: UNKNOWN
Platform: UNKNOWN
Classifier: Programming Language :: Python :: 3
Classifier: License :: OSI Approved :: MIT License
Classifier: Operating System :: OS Independent
Requires-Python: >=3.6
License-File: LICENSE
Requires-Dist: azure-cosmos
Requires-Dist: pymssql
